
Output for test1.uc:
--------------------------------------------------------------------------------
Compiled from null
public class Code extends java.lang.Object{
public static void main(java.lang.String[]);
  Code:
   0:   aload_0
   1:   arraylength
   2:   newarray int
   4:   astore_1
   5:   iconst_0
   6:   istore_2
   7:   iload_2
   8:   aload_0
   9:   arraylength
   10:  if_icmpge       28
   13:  aload_1
   14:  iload_2
   15:  aload_0
   16:  iload_2
   17:  aaload
   18:  invokestatic    #6; //Method java/lang/Integer.parseInt:(Ljava/lang/String;)I
   21:  iastore
   22:  iinc    2, 1
   25:  goto    7
   28:  aload_1
   29:  bipush  0
   31:  iaload
   32:  istore_2
   33:  getstatic       #12; //Field java/lang/System.out:Ljava/io/PrintStream;
   36:  iload_2
   37:  invokevirtual   #18; //Method java/io/PrintStream.println:(I)V
   40:  return

}
--------------------------------------------------------------------------------

Output for test2.uc:
--------------------------------------------------------------------------------
Compiled from null
public class Code extends java.lang.Object{
public static void main(java.lang.String[]);
  Code:
   0:   aload_0
   1:   arraylength
   2:   newarray int
   4:   astore_1
   5:   iconst_0
   6:   istore_2
   7:   iload_2
   8:   aload_0
   9:   arraylength
   10:  if_icmpge       28
   13:  aload_1
   14:  iload_2
   15:  aload_0
   16:  iload_2
   17:  aaload
   18:  invokestatic    #6; //Method java/lang/Integer.parseInt:(Ljava/lang/String;)I
   21:  iastore
   22:  iinc    2, 1
   25:  goto    7
   28:  aload_1
   29:  bipush  0
   31:  iaload
   32:  dup
   33:  istore  3
   35:  pop
   36:  iload   3
   38:  istore_2
   39:  getstatic       #12; //Field java/lang/System.out:Ljava/io/PrintStream;
   42:  iload_2
   43:  invokevirtual   #18; //Method java/io/PrintStream.println:(I)V
   46:  return

}
--------------------------------------------------------------------------------

Output for test3.uc (WITHOUT short-circuit evaluation):
--------------------------------------------------------------------------------
Compiled from null
public class Code extends java.lang.Object{
public static int fac(int);
  Code:
   0:   bipush  1
   2:   dup
   3:   istore  1
   5:   pop
   6:   iload   0
   8:   bipush  0
   10:  if_icmpgt       17
   13:  iconst_0
   14:  goto    18
   17:  iconst_1
   18:  ifeq    36
   21:  iload   0
   23:  iinc    0, -1
   26:  dup
   27:  iload   1
   29:  imul
   30:  istore  1
   32:  pop
   33:  goto    6
   36:  iload   1
   38:  ireturn

public static void main(java.lang.String[]);
  Code:
   0:   aload_0
   1:   arraylength
   2:   newarray int
   4:   astore_1
   5:   iconst_0
   6:   istore_2
   7:   iload_2
   8:   aload_0
   9:   arraylength
   10:  if_icmpge       28
   13:  aload_1
   14:  iload_2
   15:  aload_0
   16:  iload_2
   17:  aaload
   18:  invokestatic    #6; //Method java/lang/Integer.parseInt:(Ljava/lang/String;)I
   21:  iastore
   22:  iinc    2, 1
   25:  goto    7
   28:  aload_1
   29:  bipush  0
   31:  iaload
   32:  invokestatic    #12; //Method fac:(I)I
   35:  istore_2
   36:  getstatic       #18; //Field java/lang/System.out:Ljava/io/PrintStream;
   39:  iload_2
   40:  invokevirtual   #24; //Method java/io/PrintStream.println:(I)V
   43:  return

}
--------------------------------------------------------------------------------

Output for test4.uc
--------------------------------------------------------------------------------
Compiled from null
public class Code extends java.lang.Object{
static int counter;

public static int add(int);
  Code:
   0:   iload   0
   2:   dup
   3:   getstatic       #6; //Field counter:I
   6:   iadd
   7:   putstatic       #6; //Field counter:I
   10:  ireturn

public static void main(java.lang.String[]);
  Code:
   0:   aload_0
   1:   arraylength
   2:   newarray int
   4:   astore_1
   5:   iconst_0
   6:   istore_2
   7:   iload_2
   8:   aload_0
   9:   arraylength
   10:  if_icmpge       28
   13:  aload_1
   14:  iload_2
   15:  aload_0
   16:  iload_2
   17:  aaload
   18:  invokestatic    #12; //Method java/lang/Integer.parseInt:(Ljava/lang/String;)I
   21:  iastore
   22:  iinc    2, 1
   25:  goto    7
   28:  bipush  2
   30:  invokestatic    #16; //Method add:(I)I
   33:  pop
   34:  bipush  1
   36:  ineg
   37:  invokestatic    #16; //Method add:(I)I
   40:  istore_2
   41:  getstatic       #22; //Field java/lang/System.out:Ljava/io/PrintStream;
   44:  iload_2
   45:  invokevirtual   #28; //Method java/io/PrintStream.println:(I)V
   48:  return

}
--------------------------------------------------------------------------------

Output for test5.uc (WITHOUT short-circuit evaluation)
--------------------------------------------------------------------------------
Compiled from null
public class Code extends java.lang.Object{
public static void main(java.lang.String[]);
  Code:
   0:   aload_0
   1:   arraylength
   2:   newarray int
   4:   astore_1
   5:   iconst_0
   6:   istore_2
   7:   iload_2
   8:   aload_0
   9:   arraylength
   10:  if_icmpge       28
   13:  aload_1
   14:  iload_2
   15:  aload_0
   16:  iload_2
   17:  aaload
   18:  invokestatic    #6; //Method java/lang/Integer.parseInt:(Ljava/lang/String;)I
   21:  iastore
   22:  iinc    2, 1
   25:  goto    7
   28:  ldc     #7; //float 1.0f
   30:  dup
   31:  fstore  3
   33:  pop
   34:  aload_1
   35:  bipush  0
   37:  iaload
   38:  dup
   39:  istore  4
   41:  pop
   42:  aload_1
   43:  bipush  1
   45:  iaload
   46:  dup
   47:  istore  5
   49:  pop
   50:  iload   5
   52:  bipush  0
   54:  if_icmpgt       61
   57:  iconst_0
   58:  goto    62
   61:  iconst_1
   62:  ifeq    124
   65:  iload   5
   67:  bipush  2
   69:  irem
   70:  bipush  1
   72:  if_icmpeq       79
   75:  iconst_0
   76:  goto    80
   79:  iconst_1
   80:  ifeq    102
   83:  iload   4
   85:  i2f
   86:  dup
   87:  iload   3
   89:  imul
   90:  istore  3
   92:  pop
   93:  iload   5
   95:  iinc    5, -1
   98:  pop
   99:  goto    121
   102: iload   4
   104: dup
   105: iload   4
   107: imul
   108: istore  4
   110: pop
   111: bipush  1
   113: dup
   114: iload   5
   116: swap
   117: ishr
   118: istore  5
   120: pop
   121: goto    50
   124: fload   3
   126: f2i
   127: dup
   128: istore  4
   130: pop
   131: iload   4
   133: istore_2
   134: getstatic       #13; //Field java/lang/System.out:Ljava/io/PrintStream;
   137: iload_2
   138: invokevirtual   #19; //Method java/io/PrintStream.println:(I)V
   141: return

}

